stores/__init__.py
stores/constants.py
stores/format.py
stores/parse.py
stores/utils.py
stores/indexes/__init__.py
stores/indexes/base_index.py
stores/indexes/index.py
stores/indexes/local_index.py
stores/indexes/remote_index.py
stores/indexes/venv_utils.py
stores-0.1.6.dist-info/METADATA
stores-0.1.6.dist-info/WHEEL
stores-0.1.6.dist-info/licenses/LICENSE
stores-0.1.6.dist-info/RECORD
