Metadata-Version: 2.4
Name: stores
Version: 0.1.6
Summary: Repository of Python functions and tools for LLMs
License-File: LICENSE
Requires-Python: >=3.10
Requires-Dist: dirtyjson>=1.0.8
Requires-Dist: dotenv>=0.9.9
Requires-Dist: fuzzywuzzy>=0.18.0
Requires-Dist: gitpython>=3.1.44
Requires-Dist: makefun>=1.15.6
Requires-Dist: python-levenshtein>=0.27.1
Requires-Dist: requests>=2.32.3
Requires-Dist: tomli>=1.1.0; python_version < '3.11'
Provides-Extra: anthropic
Requires-Dist: anthropic>=0.49.0; extra == 'anthropic'
Provides-Extra: google
Requires-Dist: google-genai>=1.7.0; extra == 'google'
Provides-Extra: langchain
Requires-Dist: langchain-google-genai>=2.1.0; extra == 'langchain'
Provides-Extra: langgraph
Requires-Dist: langchain-core>=0.3.45; extra == 'langgraph'
Requires-Dist: langchain-google-genai>=2.1.0; extra == 'langgraph'
Requires-Dist: langgraph>=0.3.16; extra == 'langgraph'
Provides-Extra: litellm
Requires-Dist: litellm>=1.63.11; extra == 'litellm'
Provides-Extra: llamaindex
Requires-Dist: llama-index-llms-google-genai>=0.1.4; extra == 'llamaindex'
Requires-Dist: llama-index>=0.12.25; extra == 'llamaindex'
Provides-Extra: openai
Requires-Dist: openai>=1.66.5; extra == 'openai'
Provides-Extra: openai-agent
Requires-Dist: openai-agents>=0.0.7; extra == 'openai-agent'
